geohydrodemo/__init__.py
geohydrodemo/common.py
geohydrodemo/geohydrodemo.py
geohydrodemo-0.0.4.dist-info/LICENSE
geohydrodemo-0.0.4.dist-info/METADATA
geohydrodemo-0.0.4.dist-info/WHEEL
geohydrodemo-0.0.4.dist-info/dependency_links.txt
geohydrodemo-0.0.4.dist-info/top_level.txt
geohydrodemo-0.0.4.dist-info/RECORD
