Metadata-Version: 2.1
Name: geohydrodemo
Version: 0.0.4
Summary: A python package for interactive mapping
Home-page: https://github.com/bojichen/geohydrodemo
Author: Boji Chen
Author-email: bojichen@connect.hku.hk
License: MIT license
Keywords: geohydrodemo
Classifier: Intended Audience :: Developers
Classifier: License :: OSI Approved :: MIT License
Classifier: Natural Language :: English
Classifier: Programming Language :: Python :: 3
Classifier: Programming Language :: Python :: 3.8
Classifier: Programming Language :: Python :: 3.9
Classifier: Programming Language :: Python :: 3.10
Classifier: Programming Language :: Python :: 3.11
Requires-Python: >=3.8
License-File: LICENSE
Requires-Dist: folium
Requires-Dist: ipyleaflet
Requires-Dist: pyshp
